bspec/__init__.py
bspec/app.py
bspec/demo_config.json
bspec/common_core/dynamic_module_install.py
bspec/common_core/read_module_requirements.py
bspec/components/__init__.py
bspec/components/component_factory.py
bspec/components/pd_dataframe/__init__.py
bspec/components/pd_dataframe/pd_dataframes.py
bspec/components/pd_dataframe/requirements/module_requirements.txt
bspec/components/pd_input_dropna/__init__.py
bspec/components/pd_input_dropna/pd_input_dropna.py
bspec/components/pd_input_dropna/requirements/module_requirements.txt
bspec/components/pd_input_file_csv/__init__.py
bspec/components/pd_input_file_csv/pd_input_file_csv.py
bspec/components/pd_input_file_csv/requirements/module_requirements.txt
bspec/components/runtime_debug_print/__init__.py
bspec/components/runtime_debug_print/runtime_debug_print.py
bspec/components/runtime_debug_print/requirements/module_requirements.txt
bspec/demo_data/example_stores.csv
bspec/pipelines/__init__.py
bspec/pipelines/pd_read_and_clean_csv/__init__.py
bspec/pipelines/pd_read_and_clean_csv/pipeline.json
bspec/pipelines/pd_read_and_clean_csv/pipeline.py
bspec/plugin_core/__init__.py
bspec/plugin_core/loader.py
bspec/plugin_core/plugin_module_interface.py
bspec/processors/__init__.py
bspec/processors/processor_factory.py
bspec/processors/pd_dropna/__init__.py
bspec/processors/pd_dropna/processor.py
bspec/processors/pd_dropna/requirements/module_requirements.txt
bspec/processors/pd_read_csv/__init__.py
bspec/processors/pd_read_csv/processor.py
bspec/processors/pd_read_csv/requirements/module_requirements.txt
bspec/universe/__init__.py
bspec/universe/universe.py
BSPEC-0.1.10.dist-info/LICENSE
BSPEC-0.1.10.dist-info/METADATA
BSPEC-0.1.10.dist-info/WHEEL
BSPEC-0.1.10.dist-info/entry_points.txt
BSPEC-0.1.10.dist-info/top_level.txt
BSPEC-0.1.10.dist-info/RECORD
