Metadata-Version: 2.1
Name: BSPEC
Version: 0.1.10
Summary: A python based Plugin, Entity Component System (ECS) architecture designed with Business Specifications in mind. This package allows you to easily set up and use existing systems and components.
Author-email: Ryan Julyan <ryan@julyan.biz>
License: The BSPEC License
Project-URL: Homepage, https://github.com/BSPEC/BSPEC
Project-URL: Bug Tracker, https://github.com/BSPEC/BSPEC/issues
Keywords: ECS,Plugin,Dynamic,Dynamic
Classifier: Programming Language :: Python :: 3
Classifier: Development Status :: 2 - Pre-Alpha
Classifier: Intended Audience :: Developers
Classifier: License :: Other/Proprietary License
Classifier: Operating System :: OS Independent
Requires-Python: >=3.9
License-File: LICENSE
Requires-Dist: esper (>=2.1)
Requires-Dist: Deprecated (>=1.2.13)
Provides-Extra: dev
Requires-Dist: black ; extra == 'dev'
Requires-Dist: bumpver ; extra == 'dev'
Requires-Dist: isort ; extra == 'dev'
Requires-Dist: pip-tools ; extra == 'dev'
Requires-Dist: pytest ; extra == 'dev'
Requires-Dist: build ; extra == 'dev'
Requires-Dist: twine ; extra == 'dev'
